schemadiff/__init__.py
schemadiff/cli.py
schemadiff/filesystem.py
schemadiff/m_exceptions.py
schemadiff/report_generator.py
schemadiff/schema_comparer.py
schemadiffed-0.1.0.1.dist-info/LICENSE
schemadiffed-0.1.0.1.dist-info/METADATA
schemadiffed-0.1.0.1.dist-info/WHEEL
schemadiffed-0.1.0.1.dist-info/entry_points.txt
schemadiffed-0.1.0.1.dist-info/RECORD
