Metadata-Version: 2.1
Name: schemadiffed
Version: 0.1.0.1
Summary: Compare Parquet file schemas across different filesystems
License: MIT
Author: Elsayed91
Author-email: elsayed.is@outlook.com
Requires-Python: >=3.10,<4.0
Classifier: License :: OSI Approved :: MIT License
Classifier: Programming Language :: Python :: 3
Classifier: Programming Language :: Python :: 3.10
Classifier: Programming Language :: Python :: 3.11
Provides-Extra: aws
Provides-Extra: google
Requires-Dist: fsspec (>=2023.6.0,<2024.0.0)
Requires-Dist: gcsfs (>=2023.6.0,<2024.0.0) ; extra == "google"
Requires-Dist: pandas (>=2.0.3,<3.0.0)
Requires-Dist: pyarrow (>=12.0.1,<13.0.0)
Requires-Dist: pyyaml (>=6.0.1,<7.0.0)
Requires-Dist: s3fs (>=2023.6.0,<2024.0.0) ; extra == "aws"
